rbac_builder/__init__.py
rbac_builder/base.py
rbac_builder/base_manager.py
rbac_builder/baseview.py
rbac_builder/const.py
rbac_builder/menu.py
rbac_builder/models.py
rbac_builder/utils.py
rbac_builder/security/__init__.py
rbac_builder/security/decorators.py
rbac_builder/security/manager.py
rbac_builder/security/sqla/__init__.py
rbac_builder/security/sqla/manager.py
rbac_builder/security/sqla/models/__init__.py
rbac_builder/security/sqla/models/permission.py
rbac_builder/security/sqla/models/permission_view.py
rbac_builder/security/sqla/models/role.py
rbac_builder/security/sqla/models/view_menu.py
rbac_builder-1.0.1.dist-info/LICENSE
rbac_builder-1.0.1.dist-info/WHEEL
rbac_builder-1.0.1.dist-info/METADATA
rbac_builder-1.0.1.dist-info/RECORD
