Metadata-Version: 2.1
Name: rbac_builder
Version: 1.0.1
Summary: Role Base Access Control Builder
Home-page: https://github.com/tukida/rbac_builder
License: UNKNOWN
Author: Kidataek
Author-email: tuankiet0996@gmail.com
Classifier: License :: OSI Approved :: MIT License
